{
  "main": {
    "cardsSchema": {
      "columns": "3",
      "rows": "4"
    },
    "cardS": [
      {
        "src": "./img/2C.jpg"
      },
      {
        "src": "./img/2D.jpg"
      },
      {
        "src": "./img/2H.jpg"
      },
      {
        "src": "./img/2S.jpg"
      },
      {
        "src": "./img/3C.jpg"
      },
      {
        "src": "./img/3C.jpg"
      },
      {
        "src": "./img/3H.jpg"
      },
      {
        "src": "./img/3S.jpg"
      },
      {
        "src": "./img/4C.jpg"
      },
      {
        "src": "./img/4D.jpg"
      },
      {
        "src": "./img/4H.jpg"
      },
      {
        "src": "./img/4S.jpg"
      }
    ]
  }
}